moneymoney/__init__.py
moneymoney/currency_codes.py
moneymoney/defaults.py
moneymoney/money.py
moneymoney/presets.py
moneymoney-1.1.2.dist-info/LICENSE
moneymoney-1.1.2.dist-info/METADATA
moneymoney-1.1.2.dist-info/WHEEL
moneymoney-1.1.2.dist-info/top_level.txt
moneymoney-1.1.2.dist-info/RECORD
