Metadata-Version: 2.1
Name: moneymoney
Version: 1.1.2
Summary: Money package for Python
Author: w0rmr1d3r
License: GPLv3
Project-URL: Homepage, https://github.com/w0rmr1d3r/moneymoney
Project-URL: Repository, https://github.com/w0rmr1d3r/moneymoney
Project-URL: Bug Tracker, https://github.com/w0rmr1d3r/moneymoney/issues
Project-URL: Documentation, https://github.com/w0rmr1d3r/moneymoney
Project-URL: Changelog, https://github.com/w0rmr1d3r/moneymoney/releases
Project-URL: Funding, https://github.com/sponsors/w0rmr1d3r
Keywords: currency,python,money,finance
Classifier: Development Status :: 5 - Production/Stable
Classifier: Intended Audience :: Developers
Classifier: License :: OSI Approved :: GNU General Public License v3 (GPLv3)
Classifier: Programming Language :: Python
Classifier: Programming Language :: Python :: 3
Classifier: Programming Language :: Python :: 3.9
Classifier: Programming Language :: Python :: 3.10
Classifier: Programming Language :: Python :: 3.11
Classifier: Programming Language :: Python :: 3.12
Classifier: Topic :: Software Development :: Libraries
Requires-Python: >=3.9.0
License-File: LICENSE
Provides-Extra: dev
Requires-Dist: black >=23.0.0 ; extra == 'dev'
Requires-Dist: coverage >=6.3.2 ; extra == 'dev'
Requires-Dist: docformatter >=1.5.1 ; extra == 'dev'
Requires-Dist: flake8 >=6.0.0 ; extra == 'dev'
Requires-Dist: isort >=5.10.0 ; extra == 'dev'
Requires-Dist: pip-tools >=6.5.0 ; extra == 'dev'
Requires-Dist: pylint >=2.15.10 ; extra == 'dev'
Requires-Dist: pytest >=6.2.5 ; extra == 'dev'
